morse/__init__.py
morse/cli.py
morse/main.py
morse/utils.py
morse/assets/morse_mapping.json
morseify-1.0.0.data/data/assets/morse_mapping.json
morseify-1.0.0.dist-info/LICENSE
morseify-1.0.0.dist-info/METADATA
morseify-1.0.0.dist-info/WHEEL
morseify-1.0.0.dist-info/entry_points.txt
morseify-1.0.0.dist-info/top_level.txt
morseify-1.0.0.dist-info/RECORD
